biclustering/Pattern.py
biclustering/__init__.py
biclustering/association_rules.py
biclustering/bicluster.py
biclustering/fist.py
biclustering/frequent_patterns.py
biclustering/generators.py
biclustering/printing_util.py
biclustering/suffix_tree.py
biclustering-2023.5.31.5.dist-info/METADATA
biclustering-2023.5.31.5.dist-info/WHEEL
biclustering-2023.5.31.5.dist-info/licenses/LICENSE
biclustering-2023.5.31.5.dist-info/RECORD
