Metadata-Version: 2.1
Name: biclustering
Version: 2023.5.31.5
Summary: Biclustering and association rule mining using Suffix Tree and Frequent Closed Itemset based algorithm.
Project-URL: Homepage, https://github.com/damaclab/FIST-Biclustering-Python
Project-URL: Bug Tracker, https://github.com/damaclab/FIST-Biclustering-Python/issues
Author-email: Mijanur Rahaman Mallick <mijanur08@gmail.com>
License-File: LICENSE
Classifier: License :: OSI Approved :: MIT License
Classifier: Operating System :: OS Independent
Classifier: Programming Language :: Python :: 3
Requires-Python: >=3.10
Requires-Dist: pandas
Requires-Dist: pydot
